{"forum": {"content": "\u6bcf\u5929\u65e9\u6668\uff0c\u7167\u93e1\u5b50\u90fd\u88ab\u81ea\u5df1\u5e25\u9192", "images": ["http://filestoresg1.beetalkmobile.com:8081/file/d2b86113dd2f259ffade6908877fde4d", "http://filestoresg1.beetalkmobile.com:8081/file/3337a9b91e400d10a9d9cf2ff498ef64"], "urls": [], "title": "\u6709\u4eba\u89ba\u5f97\u81ea\u5df1\u5f88\u5e25\u55ce"}, "threadStatus": 0, "regionId": 886, "barStatus": 0, "barId": 33, "postBy": {"utc": 1437548260000, "level": 1, "location": "\u53f0\u4e2d\u5e02\u00b7\u53f0\u7063", "avatar": "http://filestoresg1.beetalkmobile.com:8081/file/5931559572897435649", "name": "K\u00c8LV\u00cdN"}, "id": 1744970}
