{"forum": {"content": "\u6211\u767c\u89ba\u6211\u53ea\u80fd\u5077\u5077\u7684 \u9ed8\u9ed8\u7684 \u5b88\u8b77\u8457\u4f60<br />\u611b\u4e00\u500b\u4eba \u53ef\u4ee5\u5f88\u6df1 \u5fd8\u4e00\u500b\u4eba \u537b\u8981\u4e00\u4e16<br /><br />\u6c92\u6709\u52c7\u6c23\u5927\u8072\u8aaa\u611b\u4f60 <br />\u6068\u81ea\u5df1\u7684\u61e6\u5f31\u2026\u2026", "images": ["http://filestoresg1.beetalkmobile.com:8081/file/563ac059144a0674a6b278705ba60071"], "urls": [], "title": "\u53ea\u80fd\u5077\u5077\u7684"}, "threadStatus": 0, "regionId": 886, "barStatus": 0, "barId": 20, "postBy": {"utc": 1438697637000, "level": 15, "location": "Taichung City\u00b7Taiwan", "avatar": "http://filestoresg1.beetalkmobile.com:8081/file/-6991128135563051418", "name": "\u5c0f\u502b"}, "id": 1839497}
