{"forum": {"content": "\u597d\u97f3\u6a02\u4e00\u8d77\u807d\u5427\uff01", "images": [], "urls": [{"url": "https://youtu.be/oI0HPoM8uX8", "thumbUrl": "https://i.ytimg.com/vi/oI0HPoM8uX8/maxresdefault.jpg", "description": "\u7537\u751f\u5728KTV\u5fc5\u6311\u6230\u7684\u6b4c\u66f2\"\u5fc3\u5982\u5200\u5272\"!!!!", "title": "\u4f0d\u4f70&China Blue [\u5fc3\u5982\u5200\u5272]\u5b98\u65b9\u5b8c\u6574\u7248HD MV"}], "title": "\u300a\u5fc3\u5982\u5200\u5272\u300b\u4f0d\u4f70"}, "threadStatus": 0, "regionId": 886, "barStatus": 0, "barId": 54, "postBy": {"utc": 1430275402000, "level": 20, "location": "\u65b0\u5317\u5e02\u00b7\u53f0\u7063", "avatar": "http://filestoresg1.beetalkmobile.com:8081/file/-7290553735229431037", "name": "\u4efb\u6027\u54e5"}, "id": 1143920}
