{"forum": {"content": "\u725b\u5976\u934b\uff5e\u63a8<br />\u5176\u4ed6\u9910\u9084\u597d<br />\u751c\u9ede\u6709\u54c8\u724c\u51b0\u6dc7\u6dcb", "images": ["http://filestoresg1.beetalkmobile.com:8081/file/61f7e7f0f3336948914e472c953b10a4", "http://filestoresg1.beetalkmobile.com:8081/file/bc7ea0ab9df60e99b184de598074d772", "http://filestoresg1.beetalkmobile.com:8081/file/1d2e84a5f730e4f0c6968c2d9bd5234b", "http://filestoresg1.beetalkmobile.com:8081/file/0720b970fb28aa3b6dc8dcb5454e101e", "http://filestoresg1.beetalkmobile.com:8081/file/d834dfae413d9ba4979993e0a8a624af", "http://filestoresg1.beetalkmobile.com:8081/file/569809e2294c1299ce7492f104f1dbef"], "urls": [], "title": "\u57d4\u5fc3\u7267\u5834\u7da0\u5eca\u9910\u5ef3"}, "threadStatus": 1, "regionId": 886, "barStatus": 0, "barId": 98, "postBy": {"utc": 1438531865000, "level": 21, "location": "\u53f0\u5317\u5e02\u00b7\u53f0\u7063", "avatar": "http://filestoresg1.beetalkmobile.com:8081/file/-7027749560854621596", "name": "\u512a\u3126"}, "id": 1826344}
