{"forum": {"content": "\u6709\u4eba\u5c08\u8077AD\u55ce??   \u6211\u5011\u6230\u968aAD\u8981\u7576\u5175\u4e86....... \u6230\u968a5.5.  \u91d12 \uff08\u5e0c\u671b\u662f\u767d\u91d1\u4ee5\u4e0a\uff09<br /><br /> \u6bcf\u5929\u665a\u4e0a8\u9ede\u56fa\u5b9a\u958b\u6253\uff0c\u6709line \u7fa4\u7d44\u3001\u7d44\u54e1\u90fd\u662f\u793e\u6703\u4eba\u58eb\u3002<br /><br />\u6709\u8208\u8da3\u7684\u7559\u8a00id\u3001main\u89d2\u3001\u724c\u4f4d\u3002<br />\u5c0d\u81ea\u5df1\u5be6\u529b\u6709\u4fe1\u5fc3\u7684\u4e5f\u53ef\u4ee5\u4f86\uff01", "images": ["http://filestoresg1.beetalkmobile.com:8081/file/e692239512b526585b89ddb41f439d8c"], "urls": [], "title": "\u6230\u968a5.5\u5fb5\u5c08\u8077adc"}, "threadStatus": 1, "regionId": 886, "barStatus": 0, "barId": 60, "postBy": {"utc": 1430374459000, "level": 1, "location": "\u53f0\u5357\u5e02\u00b7\u53f0\u7063", "avatar": "http://filestoresg1.beetalkmobile.com:8081/file/8655000394689377024", "name": "Yung Hun"}, "id": 1152940}
