{"forum": {"content": "\u6bcf\u6b21\u4e0b\u73ed\uff0c\u670b\u53cb\u90fd\u8aaa\u8a72\u7761\u4e86\u660e\u5929\u65e9\u73ed\ud83d\ude29\ud83d\ude29\ud83d\ude29", "images": ["http://filestoresg1.beetalkmobile.com:8081/file/9b815fbdb84f869e7d69888e74a9780e", "http://filestoresg1.beetalkmobile.com:8081/file/45c8efb11544bfab89689d7b846e2c67", "http://filestoresg1.beetalkmobile.com:8081/file/906e49bd9eecc76a8c6ff99518082c02", "http://filestoresg1.beetalkmobile.com:8081/file/978b1f85dc52a45b6e43e9d811bef272"], "urls": [], "title": "\u534a\u591c\u90fd\u6c92\u968a\u53cb\u554a.."}, "threadStatus": 1, "regionId": 886, "barStatus": 0, "barId": 60, "postBy": {"utc": 1432845936000, "level": 6, "location": "\u5609\u7fa9\u5e02\u00b7\u53f0\u7063", "avatar": "http://filestoresg1.beetalkmobile.com:8081/file/2668212355785532676", "name": "Steven  Chou"}, "id": 1364698}
