{"forum": {"content": "\u4f4f\u9ad8\u96c423<br />\u60f3\u627e\u6210\u719f\u4e00\u9ede\u7684\u5973\u5b69<br />\u8d95\u5feb\u628a\u6211\u9818\u8d70<br />\u6703\u6311\u7684\u5537", "images": ["http://filestoresg1.beetalkmobile.com:8081/file/37bc6bb994bccedd80446162213e5e15"], "urls": [], "title": "\u55ae\u8eab\u7684\u5973\u5b69\u9032\u4f86"}, "threadStatus": 0, "regionId": 886, "barStatus": 0, "barId": 205, "postBy": {"utc": 1439102509000, "level": 6, "location": "\u9ad8\u96c4\u5e02\u00b7\u53f0\u7063", "avatar": "http://filestoresg1.beetalkmobile.com:8081/file/-399385502661506646", "name": "\u771f\u5fc3"}, "id": 1872445}
