{"forum": {"content": "\u6211\u5728\u7b49\u4e00\u500b\u80fd\u966a\u6211\u54ed\u966a\u6211\u7b11\u7684\u53e6\u4e00\u534a\uff0c\u6216\u8a31\u59b3\u4e0d\u5b8c\u7f8e\uff0c\u4f46\u6211\u80fd\u751c\u6eff\u4e0d\u5b8c\u7f8e\uff0c\u4f46\u59b3\u6709\u672c\u4e8b\u727d\u8d77\u6211\u7684\u624b\uff0c\u5c31\u4e0d\u80fd\u653e\u624b\uff01\u56e0\u7232\u6211\u5c07\u662f\u59b3\u6700\u5b8c\u7f8e\u7684\u53e6\u4e00\u534a\uff01", "images": ["http://filestoresg1.beetalkmobile.com:8081/file/c32857e31fe494c5a6f6cf90115ad7c2"], "urls": [], "title": "\u7b49\u5f85\u3127\u500b\u4eba"}, "threadStatus": 1, "regionId": 886, "barStatus": 0, "barId": 205, "postBy": {"utc": 1432710198000, "level": 6, "location": "\u6843\u5712\u5e02\u00b7\u53f0\u7063", "avatar": "http://filestoresg1.beetalkmobile.com:8081/file/-2721465001042043639", "name": "Ken"}, "id": 1352849}
