{"forum": {"content": "\u4f86\u5427\u6b61\u8fce\u4f60\u5011<br /><br />\u4e0d\u7ba1\u4f60\u5011\u662f \u8e22\u8e22\u6216\u6279\u8e22 \u6216\u6279\u6279<br /><br />\u90fd\u6b61\u8fce\u4f60\u5011<br /><br />", "images": ["http://filestoresg1.beetalkmobile.com:8081/file/754b51b4b147f7118e33088b308a6c93"], "urls": [], "title": "\u62c9\u5b50\u804a\u5929"}, "threadStatus": 1, "regionId": 886, "barStatus": 0, "barId": 20, "postBy": {"utc": 1432702796000, "level": 10, "location": "\u53f0\u4e2d\u5e02\u00b7\u53f0\u7063", "avatar": "http://filestoresg1.beetalkmobile.com:8081/file/-7139033334929227772", "name": "\u8587\u8587"}, "id": 1352088}
