{"forum": {"content": "\u770b\u4e86\u516b\u4ed9\u6a02\u5712\u7684\u706b\u707d\u65b0\u805e\uff0c\u611f\u89ba\u597d\u96e3\u904e?", "images": ["http://filestoresg1.beetalkmobile.com:8081/file/2a3d0bf02d5fdc6f501e58ed4121ad9e"], "urls": [], "title": "\u96e3\u904e"}, "threadStatus": 1, "regionId": 886, "barStatus": 0, "barId": 205, "postBy": {"utc": 1435516063000, "level": 7, "location": "Taichung City\u00b7Taiwan", "avatar": "http://filestoresg1.beetalkmobile.com:8081/file/2474362965228474937", "name": "\u5b8f\u6b38"}, "id": 1583733}
