{"forum": {"content": "\u597d\u7dca\u5f35\u311a> \u03c9<<br /><br />\u660e\u5929\u8981\u6703\u8003\u4e86.....<br /><br />\u60f3\u5fc5\u9019\u5c07\u6703\u4f60\u6b7b\u6211\u6d3b\u7684\u6fc0\u70c8\u7af6\u722d\u3002<br /><br />\u9001\u4e0a\u3127\u5f35\u8003\u524d\u4e0d\u5b89\u7167<br /><br />\u795d\u798f\u8003\u751f\u5011\u8003\u53d6\u4e0a\u81ea\u5df1\u7684\u7b2c\u4e00\u5fd7\u9858\u311a~~<br /><br />\u52a0\u6cb9\u52a0\u6cb9", "images": ["http://filestoresg1.beetalkmobile.com:8081/file/b9b81be5ccdc8e4f77de3b81c734c971", "http://filestoresg1.beetalkmobile.com:8081/file/ad65a8489671db1a94e7c2b0f0b650d4", "http://filestoresg1.beetalkmobile.com:8081/file/0be28c5bec34d63486eab4d8f65147ea", "http://filestoresg1.beetalkmobile.com:8081/file/ea7d05887c30991df28f39a4ca6fd938"], "urls": [], "title": "\u570b\u4e09\u6703\u8003\u52a0\u6cb9~~~"}, "threadStatus": 1, "regionId": 886, "barStatus": 0, "barId": 512, "postBy": {"utc": 1431690299000, "level": 2, "location": "", "avatar": "http://filestoresg1.beetalkmobile.com:8081/file/-4523820739160532478", "name": "Bono"}, "id": 1266959}
