{"forum": {"content": "\u597d\u71b1~\u597d\u7d2f\u5537\uff01<br />\u53c8\u662f\u4e00\u500b\u6c57\u5982\u96e8\u4e0b\u7684\u591c\u2026\u2026", "images": ["http://filestoresg1.beetalkmobile.com:8081/file/c9c35a72c2c4a2939967d7d5d2ea142e"], "urls": [], "title": "\u6fd5\u900f\u4e86\u2026\u2026"}, "threadStatus": 0, "regionId": 886, "barStatus": 0, "barId": 4, "postBy": {"utc": 1433778177000, "level": 4, "location": "\u6843\u5712\u5e02\u00b7\u53f0\u7063", "avatar": "http://filestoresg1.beetalkmobile.com:8081/file/2118909551445097622", "name": "Lucifer"}, "id": 1439565}
