{"forum": {"content": "\u751f\u6d3b\u7e3d\u662f\u5f88\u5fd9<br />\u4f46\u5167\u5fc3\u5f88\u7a7a<br /><br />\u8ff7\u8def\u7684\u4ed6\u5462\uff1f<br />\u70ba\u4ec0\u9ebc\u4e0d\u5feb\u9ede\u4f86\u6211\u8eab\u908a<br />\u96e3\u9053\u80d6\u80d6\u6c92\u4eba\u611b\u55ce", "images": ["http://filestoresg1.beetalkmobile.com:8081/file/035138b77f4543896297b2898797998f", "http://filestoresg1.beetalkmobile.com:8081/file/c7453288651dbbf86b7996ba99e3dd95", "http://filestoresg1.beetalkmobile.com:8081/file/f707ba959ff8589ac8863fc87094fe41"], "urls": [], "title": "\u4e0d\u7fd2\u6163\u5bc2\u5bde"}, "threadStatus": 1, "regionId": 886, "barStatus": 0, "barId": 205, "postBy": {"utc": 1433775780000, "level": 10, "location": "\u53f0\u4e2d\u5e02\u00b7\u53f0\u7063", "avatar": "http://filestoresg1.beetalkmobile.com:8081/file/1708534419696235567", "name": "sherry\ud83d\udc49\u5fc3\u5df2\u6b7b\ud83d\udc3e"}, "id": 1439260}
