{"forum": {"content": "\u8dea\u6c42\u7a4d\u5206\u6c42\u91d1\u724c<br /><br /><br />id:rainbow_eisa", "images": ["http://filestoresg1.beetalkmobile.com:8081/file/c25dd040209cf923799031560e9e0748"], "urls": [], "title": "\u5e36\u6211\u6253\u7a4d\u5206\u561b\ud83d\ude22\ud83d\ude22\ud83d\ude22"}, "threadStatus": 0, "regionId": 886, "barStatus": 0, "barId": 60, "postBy": {"utc": 1433383708000, "level": 3, "location": "\u53f0\u4e2d\u5e02\u00b7\u53f0\u7063", "avatar": "http://filestoresg1.beetalkmobile.com:8081/file/6715170510742515771", "name": "C.Y"}, "id": 1407084}
