{"forum": {"content": "\u570b\u4e00\u5c41\u5b69\ud83d\ude06<br />IG:01_L<br />\u4e92\u8ffd\u4e92\u8b9a\ud83d\ude0a\ud83d\ude0a\ud83d\ude0a", "images": ["http://filestoresg1.beetalkmobile.com:8081/file/00cc9e2d6d790ddb805021e077f8a9bf", "http://filestoresg1.beetalkmobile.com:8081/file/2b10fdbf55cae107e952b3ed9decdc47"], "urls": [], "title": "IG\u7d66\u4e0d\u7d66\u8ffd?"}, "threadStatus": 1, "regionId": 886, "barStatus": 0, "barId": 512, "postBy": {"utc": 1434890473000, "level": 2, "location": "\u65b0\u5317\u5e02\u00b7\u53f0\u7063", "avatar": "http://filestoresg1.beetalkmobile.com:8081/file/3382616741989751097", "name": "\u601d\u601d \uc0ac\uc601"}, "id": 1530166}
