{"forum": {"content": "Mayu Wakisaka_24 Hours", "images": [], "urls": [{"url": "https://www.youtube.com/watch?v=2STSV_mUAq4", "thumbUrl": "https://i.ytimg.com/vi/2STSV_mUAq4/default.jpg", "description": "Sony Walkman\u306e\u30d7\u30ec\u30ed\u30fc\u30c9\u30bd\u30f3\u30b0\u306b\u3082\u63a1\u7528\u3055\u308c\u3001\u56fd\u5185\u5916\u3067\u8a71\u984c\u3092\u547c\u3093\u3060Mayu Wakisaka\u306e\"24 Hours\"\u306e\u30aa\u30d5\u30a3\u30b7\u30e3\u30eb\u30d3\u30c7\u30aa\u30af\u30ea\u30c3\u30d7\uff01\n\u5225\u308c\u307e\u3067\u306e24\u6642\u9593\u3092\u30ab\u30a6\u30f3\u30c8\u30c0\u30a6\u30f3\u3057\u305f\u5207\u306a\u3044", "title": "Mayu Wakisaka \"24 Hours\" (Official Music Video)"}], "title": "[\u82f1\u8a9e]Mayu Wakisaka_24 Hours"}, "threadStatus": 0, "regionId": 886, "barStatus": 0, "barId": 54, "postBy": {"utc": 1430454573000, "level": 8, "location": "\u53f0\u5317\u5e02\u00b7\u53f0\u7063", "avatar": "http://filestoresg1.beetalkmobile.com:8081/file/5777497106684562250", "name": "\u611a\u4ec1\u5091"}, "id": 1159579}
