{"forum": {"content": "\u6211\u4e0d\u592a\u4e3b\u52d5\u8b1d\u8b1d~<br />\u4f46\u7559\u8a00\u6211\u76e1\u91cf\u90fd\u4e3b\u52d5+++<br />\ud83d\ude0a", "images": ["http://filestoresg1.beetalkmobile.com:8081/file/176f668ac0638ee9f0b050489950bee1"], "urls": [], "title": "\u5927\u5bb6\u597d\u54c7\ud83d\ude04"}, "threadStatus": 1, "regionId": 886, "barStatus": 0, "barId": 4, "postBy": {"utc": 1436191087000, "level": 0, "location": "\u53f0\u5357\u5e02\u00b7\u53f0\u7063", "avatar": "http://filestoresg1.beetalkmobile.com:8081/file/3735738094847749376", "name": "\u02d9\u02d9"}, "id": 1637507}
