{"forum": {"content": "\u670d\u52d9\u696d\u7684\u98b1\u98a8\u5047<br />\u8cf4\u5728\u5bb6\u804a\u804a\u5929\u5566\uff5e", "images": ["http://filestoresg1.beetalkmobile.com:8081/file/adf952f466984c442b08d79d2c118b41"], "urls": [], "title": "\u98b1\u98a8\u5047"}, "threadStatus": 1, "regionId": 886, "barStatus": 0, "barId": 4, "postBy": {"utc": 1439022915000, "level": 7, "location": "\u53f0\u5357\u5e02\u00b7\u53f0\u7063", "avatar": "http://filestoresg1.beetalkmobile.com:8081/file/-8239804998201061868", "name": "Star"}, "id": 1865804}
