{"forum": {"content": "\u4e0d\u77e5\u9053\u8981\u7528\u4ec0\u9ebc\u6a19\u984c<br />\u600e\u9ebc\u641e\u90fd\u597d\u9ce5<br />\u4f46\u6211\u53ea\u60f3\u767c\u81ea\u62cd\u7167\ud83d\ude2d\ud83d\ude2d\ud83d\ude2d\ud83d\ude2d", "images": ["http://filestoresg1.beetalkmobile.com:8081/file/1c220f397b335d950958c855e12fe7ad", "http://filestoresg1.beetalkmobile.com:8081/file/5180b4b3cbd35d2d1343050c6ba19f0e"], "urls": [], "title": "\u6211\u53ea\u662f\u60f3po\u81ea\u62cd..."}, "threadStatus": 1, "regionId": 886, "barStatus": 0, "barId": 205, "postBy": {"utc": 1433134679000, "level": 8, "location": "", "avatar": "http://filestoresg1.beetalkmobile.com:8081/file/8613113397801133068", "name": "Mina"}, "id": 1386926}
