{"forum": {"content": "\u56de\u4f86\u9084\u8981\u7e7c\u7e8c\u5927\u591c\u73ed", "images": ["http://filestoresg1.beetalkmobile.com:8081/file/3ea99599d52116ff5585a748378434f8"], "urls": [], "title": "\u51fa\u767c\u9ad8\u96c4\u7206\u809d\u4e2d"}, "threadStatus": 0, "regionId": 886, "barStatus": 0, "barId": 4, "postBy": {"utc": 1433131597000, "level": 2, "location": "\u5609\u7fa9\u7e23\u00b7\u53f0\u7063", "avatar": "http://filestoresg1.beetalkmobile.com:8081/file/-6769584234089085175", "name": "\u8c6c\u53ef\u6bba\u4e0d\u53ef\u6ef7"}, "id": 1386651}
