{"forum": {"content": "\u539f\u4f86\u8a50\u9a19\u96c6\u5718\u4e5f\u5f88\u6703\u5634\u6ce1<br />\u7b2c\u4e8c\u96c6", "images": ["http://filestoresg1.beetalkmobile.com:8081/file/b208ce1b6a73a0bc0186a3835663a66b", "http://filestoresg1.beetalkmobile.com:8081/file/5381791d1cf42f8a0a5eb260c54abe13", "http://filestoresg1.beetalkmobile.com:8081/file/c232923d284cf55d36596cf74e86b5cf", "http://filestoresg1.beetalkmobile.com:8081/file/47c4d627aee32d93786f17326be771c2", "http://filestoresg1.beetalkmobile.com:8081/file/ad4cefab6feef6ddef28e76e56688baa", "http://filestoresg1.beetalkmobile.com:8081/file/4c2854c394be3d505a57574d7b0d0b9a"], "urls": [], "title": "\u8a50\u9a19\u96c6\u5718"}, "threadStatus": 0, "regionId": 886, "barStatus": 0, "barId": 10, "postBy": {"utc": 1432270323000, "level": 10, "location": "\u65b0\u7af9\u7e23\u00b7\u53f0\u7063", "avatar": "http://filestoresg1.beetalkmobile.com:8081/file/7648772687604959397", "name": "\u62db\u8ca1\u8c93"}, "id": 1315961}
