{"forum": {"content": "\u6709\u9ede\u60f3\u6253\u5730\u9f20\u7684\u611f\u89ba\u2026\u2026^\u76bf^", "images": ["http://filestoresg1.beetalkmobile.com:8081/file/ff93a9702893dc7e8a900b87b3a2f9a0", "http://filestoresg1.beetalkmobile.com:8081/file/3b604eb886157cb080924b6fe6643811", "http://filestoresg1.beetalkmobile.com:8081/file/7e88a056d2404a11bc799ca6377dd7b0", "http://filestoresg1.beetalkmobile.com:8081/file/bf9f7532f0b1584745b35cc03f3449f8", "http://filestoresg1.beetalkmobile.com:8081/file/f5282eeb202f3d4f6dd25653757d1b8d", "http://filestoresg1.beetalkmobile.com:8081/file/0c16bb527a06a3d7a59cba55c0feeda5"], "urls": [], "title": "\u6700\u8fd1\u559c\u6b61\u8eb2\u7d19\u7bb1"}, "threadStatus": 0, "regionId": 886, "barStatus": 0, "barId": 105, "postBy": {"utc": 1430500736000, "level": 3, "location": "", "avatar": "http://filestoresg1.beetalkmobile.com:8081/file/-7949912170505691648", "name": "\u548c"}, "id": 1164372}
