{"forum": {"content": "\u54c8\u56c9\uff0c\u5927\u5bb6\u597d\uff0c\u6211\u5347\u570b\u4e09<br />\u7136\u5f8c\uff0c\u55ef...\u53ef\u4ee5\u7684\u8a71<br />\u53ef\u4ee5\u8ddf\u4f60\u5011\u7576\u670b\u53cb\u561b\uff1f<br />\u55ef...\u5fc3\u60c5\u4e0d\u597d\u7684\u8a71<br />\u53ef\u4ee5\u4f86\u627e\u6211\u804a\u804a<br />\u6709\u95dc\u611b\u60c5\u7684\u4e8b\uff0c\u4e5f\u662f\u53ef\u4ee5\u8ddf\u6211\u804a<br />\u6211\u53ef\u4ee5\u5e6b\u4f60\u5011\uff01<br /><br />\u6211\u4eba\u5f88\u597d\u76f8\u8655^^", "images": ["http://filestoresg1.beetalkmobile.com:8081/file/77016c3b68f7eaf846d7f8b81d08f04f", "http://filestoresg1.beetalkmobile.com:8081/file/78ffbc3f5576e1e31b8092d5a91e245d"], "urls": [], "title": "^_^\u591a\u6307\u6559##"}, "threadStatus": 0, "regionId": 886, "barStatus": 0, "barId": 512, "postBy": {"utc": 1436200043000, "level": 2, "location": "\u53f0\u4e2d\u5e02\u00b7\u53f0\u7063", "avatar": "http://filestoresg1.beetalkmobile.com:8081/file/-8279026781226501583", "name": "\u5a77\u5a77.\ud83c\udf39"}, "id": 1638665}
