{"forum": {"content": "\u5929\u71b1\u4e86\uff01\uff01\uff01\u518d\u628a\u539a\u91cd\u3001\u6df1\u8272\u7684\u773c\u599d\u756b\u5728\u81c9\u4e0a\u5c31low\u6389\u56c9\uff01", "images": ["http://filestoresg1.beetalkmobile.com:8081/file/880779dda04234c67ce594a15a5ed547", "http://filestoresg1.beetalkmobile.com:8081/file/c1eb76bce7cc7bf44ecb5d2a69aa80b1", "http://filestoresg1.beetalkmobile.com:8081/file/3d0e90cd55f00ecd59e6ea1b39c7c889"], "urls": [], "title": "\u6625\u590f\u6e05\u723d\u8cea\u611f\u599d\u5bb9"}, "threadStatus": 0, "regionId": 886, "barStatus": 0, "barId": 36, "postBy": {"utc": 1433193057000, "level": 2, "location": "\u9ad8\u96c4\u5e02\u00b7\u53f0\u7063", "avatar": "http://filestoresg1.beetalkmobile.com:8081/file/2165745438369155842", "name": "Mia"}, "id": 1392534}
