{"forum": {"content": "\u5982\u6a19\u984c\u81ea\u8a8d\u70ba\u597d\u7537\u4eba<br />\u70ba\u4ec0\u9ebc\u9019\u9ebc\u8a8d\u70ba\u5462\uff1f<br />\u56e0\u70ba\u6211\u78ba\u5be6\u662f\u500b\u597d\u7537\u4eba\u5c31\u9019\u6a23<br /><br />\u55ae\u8eab\u60f3\u7a69\u5b9a\u4ea4\u5f80\u7684\u4f60<br />\u5feb\u4f86\u7d66\u6211\u75bc\u5427\uff01<br />\u6211169-65-24<br /><br />\u677f\u6a4b\u4eba\u4f73\uff0c\u5e74\u7d00\u76f8\u4eff\uff0c\u4e0d\u5316\u6fc3\u599d\uff0c<br /><br />\u60f3\u8a8d\u8b58\u518d\u4f86\uff0c\u4e0d\u8981\u96a8\u4fbf\u73a9\u73a9\uff01", "images": ["http://filestoresg1.beetalkmobile.com:8081/file/6bccc0ad01cd5f0e46c44e828de59ba4", "http://filestoresg1.beetalkmobile.com:8081/file/ecda5194cd8f9a0daf8ec41ea87c79d7"], "urls": [], "title": "\u597d\u7537\u4eba\uff0c\u4e0d\u5e36\u8d70\uff1f"}, "threadStatus": 0, "regionId": 886, "barStatus": 0, "barId": 205, "postBy": {"utc": 1435846999000, "level": 2, "location": "\u65b0\u5317\u5e02\u00b7\u53f0\u7063", "avatar": "http://filestoresg1.beetalkmobile.com:8081/file/-2562913224033895931", "name": "\u6b50\u6bd4\u5eb7"}, "id": 1609619}
