{"forum": {"content": "\u8001\u6885\u77f3\u69fd", "images": ["http://filestoresg1.beetalkmobile.com:8081/file/b053891d1c720a5f9a3d8e4037189b33", "http://filestoresg1.beetalkmobile.com:8081/file/20a880451336e0521748ac355554f077", "http://filestoresg1.beetalkmobile.com:8081/file/a6047eb408bd0ce02fd8aeec9554e0c0", "http://filestoresg1.beetalkmobile.com:8081/file/e8a32f44d6513b857466143c7571cb69", "http://filestoresg1.beetalkmobile.com:8081/file/dccf334b56451fb6ca31d20763b8e7a4", "http://filestoresg1.beetalkmobile.com:8081/file/c32b583fb2334047850766df83e6987c"], "urls": [], "title": "\u771f\u7684\u4e0d\u77e5\u9053\u600e\u6a23\u62cd\u6bd4\u8f03\u597d"}, "threadStatus": 0, "regionId": 886, "barStatus": 0, "barId": 77, "postBy": {"utc": 1432087287000, "level": 6, "location": "", "avatar": "http://filestoresg1.beetalkmobile.com:8081/file/2207121159633815296", "name": "LOST\u337f\u6d6a\u8de1\u5929\u6daf\u6d41\u6d6a\u8c93\u0d9a"}, "id": 1300170}
