{"forum": {"content": "\u6211\u8cb7\u4e86\u4e00\u53f0\u4e8c\u624b\u8ca8\uff0c\u5169\u5e74\u8eca\uff0c\u4f46\u907f\u9707\u5668\u611f\u89ba\u8edf\u8edf\u7684\uff0c\u4e5f\u7121\u6cd5\u5f9e\u56db\u64cb\u76f4\u63a5\u8e29\u5230\u7a7a\u6a94\uff0c\u662f\u88ab\u9a0e\u58de\u55ce\uff1f\u53e6\u5916\u4e5f\u60f3\u63db\u8072\u97f3\u597d\u807d\u7684\u6392\u6c23\u7ba1\uff0c\u8acb\u554f\u6709\u4eba\u80fd\u5206\u4eab\u6216\u662f\u63a8\u85a6\u55ce\uff1f", "images": ["http://filestoresg1.beetalkmobile.com:8081/file/5ea704917403bc32851b5ee016603d0f"], "urls": [], "title": "\u95dc\u65bcSYM T2"}, "threadStatus": 0, "regionId": 886, "barStatus": 0, "barId": 73, "postBy": {"utc": 1429770872000, "level": 2, "location": "\u9ad8\u96c4\u5e02\u00b7\u53f0\u7063", "avatar": "http://filestoresg1.beetalkmobile.com:8081/file/1577300478680983312", "name": "\u5fd7\u7f8e\u9ec3"}, "id": 1095240}
