{"forum": {"content": "\u55e8\u55e8<br />\u6709\u6c92\u6709\u8981\u559c\u6b61\u6211\u5011\u5462\uff1f<br />\u67f4\u67f4\u813e\u6c23\u4e0d\u662f\u84cb\u8cc0<br />\u4e3b\u4eba\u813e\u6c23\u525b\u597d\u985b\u5012", "images": ["http://filestoresg1.beetalkmobile.com:8081/file/f8a6c0132236d02219444a0f86ae2871", "http://filestoresg1.beetalkmobile.com:8081/file/b4c4eccb4de283a320cac6c723b22a7b"], "urls": [], "title": "\u4f86\u5427\uff01\u6709\u6c92\u6709\u4eba\u8981\u559c\u6b61\u6211\u5011\u5462\uff1f"}, "threadStatus": 0, "regionId": 886, "barStatus": 0, "barId": 205, "postBy": {"utc": 1439517878000, "level": 3, "location": "\u53f0\u5357\u5e02\u00b7\u53f0\u7063", "avatar": "http://filestoresg1.beetalkmobile.com:8081/file/2958187657005317643", "name": "Cheung"}, "id": 1905445}
