{"forum": {"content": "\u54c8\u54c8\u55e8\uff0c\u5348\u5b89~~\ud83d\ude02", "images": ["http://filestoresg1.beetalkmobile.com:8081/file/72566a2c6a1a33132f9984fbc91e3343"], "urls": [], "title": "\u8a72\u8aaa\u4ec0\u9ebc\u597d\u5462 "}, "threadStatus": 1, "regionId": 886, "barStatus": 0, "barId": 4, "postBy": {"utc": 1439955723000, "level": 1, "location": "\u53f0\u4e2d\u5e02\u00b7\u53f0\u7063", "avatar": "http://filestoresg1.beetalkmobile.com:8081/file/4888603532179914509", "name": "\ud83c\udf38\u3105\u311f\u02cb\ud83c\udf38"}, "id": 1940675}
