{"forum": {"content": "\u6211\u4e0d\u662f\u5973\u795e", "images": ["http://filestoresg1.beetalkmobile.com:8081/file/12899427234bc440a3b6b0dc40be0d2a", "http://filestoresg1.beetalkmobile.com:8081/file/73cac1d535b70532bec5650400945d50", "http://filestoresg1.beetalkmobile.com:8081/file/8b21fb7be349e9503a07de86341b06ab", "http://filestoresg1.beetalkmobile.com:8081/file/4922a3303ef085bd519506b804616a79", "http://filestoresg1.beetalkmobile.com:8081/file/50b44b5b31a21086cd8399e04cc9f3ce", "http://filestoresg1.beetalkmobile.com:8081/file/22e9aecfee89a100e809cabfe5083a71"], "urls": [], "title": "\u65b0\u7167\u7247"}, "threadStatus": 0, "regionId": 886, "barStatus": 0, "barId": 32, "postBy": {"utc": 1432210795000, "level": 18, "location": "", "avatar": "http://filestoresg1.beetalkmobile.com:8081/file/1377987145235187986", "name": "\ud83c\udf39\ud83d\udc9e\u4f50\u85e4\u827e\u82b8\ud83d\udc9e\ud83c\udf39"}, "id": 1311309}
