{"forum": {"content": "\u6f02\u4e0d\u6f02\u4eae\u6c92\u6709\u95dc\u4fc2<br />\u6211\u8981\u7684\u662f\u59b3\u611b\u6211\u7684\u5fc3<br />\u6703\u5f88\u96e3\u561b<br /><br />\u4eba\u672c\u4f86\u5c31\u4e0d\u662f\u5b8c\u7f8e\u7684<br />\u5c0d\u5427\uff01<br /><br />\u6211\u5f88\u9ecf\u4eba<br />\u9577\u7684\u6c92\u5f88\u5e25<br />\u9019\u4e9b\u6211\u90fd\u77e5\u9053<br />\u4f46\u91cd\u8981\u7684\u662f\u5fc3\u5427<br /><br />\u4e00\u63a8\u770b\u5916\u8868\u771f\u7684\u5f88\u8a0e\u53ad<br /><br />", "images": ["http://filestoresg1.beetalkmobile.com:8081/file/4d15ea720647ab3dfcc6b920f7708676"], "urls": [], "title": "\u627e\u500b\u771f\u5fc3\u7684"}, "threadStatus": 1, "regionId": 886, "barStatus": 0, "barId": 383, "postBy": {"utc": 1439378904000, "level": 1, "location": "\u65b0\u5317\u5e02\u00b7\u53f0\u7063", "avatar": "http://filestoresg1.beetalkmobile.com:8081/file/8229459715393159333", "name": "\u5f35\u9b5a\u9b5a"}, "id": 1894997}
