{"forum": {"content": "JsHHES \u9019\u5bc6\u78bc\u662f\u627e\u5230\u9996\u6b4c\u55ce\uff1f<br /><br />\u6211\u627e\u5230\u7684\u662f\u6587\u7ae0\u22ef\u6709\u4eba\u77e5\u9053\u55ce\uff1f", "images": ["http://filestoresg1.beetalkmobile.com:8081/file/aea7d6d5cf9db6755372041bbeaba9aa"], "urls": [], "title": "Mibble \u768412\u9996\u6b4c"}, "threadStatus": 0, "regionId": 886, "barStatus": 0, "barId": 546, "postBy": {"utc": 1440131771000, "level": 3, "location": "", "avatar": "http://filestoresg1.beetalkmobile.com:8081/file/5584589987019419199", "name": "\u5361\u4e0d\u9a0eNO"}, "id": 1955627}
