{"forum": {"content": "\u53ef\u4e0d\u53ef\u4ee5\u525b\u597d\u59b3\u4e5f\u559c\u6b61\u6211", "images": ["http://filestoresg1.beetalkmobile.com:8081/file/63a8f6f9d1ae9cade08710762bd5499a"], "urls": [], "title": "\u55ae\u8eab\u7121\u7f6a"}, "threadStatus": 0, "regionId": 886, "barStatus": 0, "barId": 205, "postBy": {"utc": 1439573972000, "level": 3, "location": "\u9ad8\u96c4\u5e02\u00b7\u53f0\u7063", "avatar": "http://filestoresg1.beetalkmobile.com:8081/file/8202358946973264827", "name": "William"}, "id": 1910979}
