{"forum": {"content": "\u9019\u4e9b\u662fLINE\u55b5\u4e16\u754c\u5927\u5bb6\u7684\u975e\u5b98\u65b9\u5537w<br />\u52a0\u4e00\u4e0b\u5427OwO<br /><br />\u8c93\u8c93:@OWB8907D<br />\u9b3c\u9b3c:@JON2390W<br />\u9ed1\u8c93:@HVM3440S<br />\u5e0c:@ESH2433L<br />\u5e7b\u591c:@ISD3058R<br /><br />\u500b\u500b\u90fd\u662f\u53ef\u611b\u7684\u8c93\u5152\u5537OwO<br />\u4e0b\u9762\u5716\u7247\u6709\u4e9b\u662f\u6c92\u8fa6\u975e\u5b98\u65b9\u7684\u5537w<br />\u4f46\u662f\u4e00\u6a23\u662f\u6211\u5011\u55b5\u4e16\u754c\u7684\u6210\u54e1\u5462OwO", "images": ["http://filestoresg1.beetalkmobile.com:8081/file/f7885df1e1b5512fc980d8f5624cda6c", "http://filestoresg1.beetalkmobile.com:8081/file/c13ef206a9e97d4a846a4051864d6004"], "urls": [], "title": "\u770b\u4e00\u4e0b\u5427OwO"}, "threadStatus": 1, "regionId": 886, "barStatus": 0, "barId": 422, "postBy": {"utc": 1430681523000, "level": 25, "location": "\u53f0\u5357\u5e02\u00b7\u53f0\u7063", "avatar": "http://filestoresg1.beetalkmobile.com:8081/file/-581555886324711708", "name": "\u6cd5\u862d\u514b\u65af\u6ce2\u65af\u8c93\u8207\u7d05\u9bc9\u9b5a\u8207\u7da0\u9bc9\u8207\u9a62"}, "id": 1180397}
