{"forum": {"content": "\u8aaa\u6389\u4e86\u537b\u4e0d\u7d66\u64bf\uff1f\u6a19\u6e96\u592a\u9ad8\u9084\u662f\u96a8\u4fbf\u8aaa\u8aaa\uff0c\u62ff\u8aa0\u610f\u51fa\u4f86\u770b\u770b\u7d66\u8cf4\u7d66\u804a\uff0c\u624d\u662f\u91cd\u9ede\u3002", "images": ["http://filestoresg1.beetalkmobile.com:8081/file/8b111850ea025634a7d1388b3fe6bbfb"], "urls": [], "title": "\u662f\u6389\u9084\u662f\u91e3\uff1f"}, "threadStatus": 0, "regionId": 886, "barStatus": 0, "barId": 383, "postBy": {"utc": 1431799162000, "level": 3, "location": "\u65b0\u5317\u5e02\u00b7\u53f0\u7063", "avatar": "http://filestoresg1.beetalkmobile.com:8081/file/3967107224244281090", "name": "\u5c0f\u9ea5"}, "id": 1276401}
