{"forum": {"content": "\u7b49\u5f85\u8457\u90a3\u500b\u4eba\u53ef\u4ee5\u627e\u5230\u6211", "images": ["http://filestoresg1.beetalkmobile.com:8081/file/423221fa2d13a8e96bfffc2e20b60bb5", "http://filestoresg1.beetalkmobile.com:8081/file/9869b5e664407a036d2b8c2b6bf1aefa", "http://filestoresg1.beetalkmobile.com:8081/file/56409bbda4545a725a2c6d88a30752fc"], "urls": [], "title": "\u7b49\u5f85"}, "threadStatus": 1, "regionId": 886, "barStatus": 0, "barId": 205, "postBy": {"utc": 1433489448000, "level": 1, "location": "\u5f70\u5316\u7e23\u00b7\u53f0\u7063", "avatar": "http://filestoresg1.beetalkmobile.com:8081/file/4849448811888462848", "name": "Lin"}, "id": 1415981}
