{"forum": {"content": "\u600e\u4e48\u57f9\u517b\u81ea\u5df1\u7f8e\u611f\u554a\uff01\u6c42\u89e3", "images": ["http://filestoresg1.beetalkmobile.com:8081/file/ba5709ef63ed0f7015761a73562723f9"], "urls": [], "title": "\u7f8e\u611f\u5728\u54ea\uff1f"}, "threadStatus": 1, "regionId": 886, "barStatus": 0, "barId": 4, "postBy": {"utc": 1431009830000, "level": 2, "location": "\u53f0\u6e7e\u7701\u00b7", "avatar": "http://filestoresg1.beetalkmobile.com:8081/file/-4036818457062496253", "name": "Lhy"}, "id": 1209545}
