{"forum": {"content": "\u53ef\u4ee5\u885d \u9810\u544a\u7247\u914d\u6a02\u4e5f\u8d85\u5438\u5f15\u4eba\u7684", "images": [], "urls": [{"url": "http://youtu.be/pWuO3Tv5yXA", "thumbUrl": "https://i.ytimg.com/vi/pWuO3Tv5yXA/default.jpg", "description": "\u300a\u7dad\u591a\u8389\u4e9e\u300b Victoria\n\n\u8056\u8cfd\u5df4\u65af\u8482\u5b89\u5e2d\u5df4 Sebastian Schipper \n\n2015|\u5fb7\u570b|DCP|Colour|140\u5206\n\n2015 \u67cf\u6797\u5f71\u5c55\u6700\u4f73\u651d\u5f71\u9280\u718a\u734e \n\n\u7dad\u591a\u8389\u4e9e\u5728\u8df3\u821e\uff0c\u5979", "title": "2015\u53f0\u5317\u96fb\u5f71\u7bc0\uff5c\u7dad\u591a\u8389\u4e9e Victoria"}], "title": "\u4e00\u93e1\u5230\u5e95\u300c\u7dad\u591a\u8389\u4e9e\u300d"}, "threadStatus": 0, "regionId": 886, "barStatus": 0, "barId": 47, "postBy": {"utc": 1439176589000, "level": 2, "location": "\u65b0\u5317\u5e02\u00b7\u53f0\u7063", "avatar": "http://filestoresg1.beetalkmobile.com:8081/file/2469699935229392147", "name": "Em"}, "id": 1878315}
