{"forum": {"content": "\u804a\u5929\u804a\u5929 \ud83d\ude01", "images": ["http://filestoresg1.beetalkmobile.com:8081/file/d04f030a85cfd5ffdaf0ed772d2c27e9", "http://filestoresg1.beetalkmobile.com:8081/file/19127619c2af9a20f6d8f3c3c7ae09ac", "http://filestoresg1.beetalkmobile.com:8081/file/0ac06c5df7483869a31551ae1cbd6e97", "http://filestoresg1.beetalkmobile.com:8081/file/78c3bb0ba66035bb83a25f3a34e4424a", "http://filestoresg1.beetalkmobile.com:8081/file/f70dd67a4a601c52e161bdf7f19e6264", "http://filestoresg1.beetalkmobile.com:8081/file/380aa70221efbe2faa130667460eb1b3"], "urls": [], "title": "\u54c7 \u5927\u5bb6\u90fd\u597d\u5e25"}, "threadStatus": 0, "regionId": 886, "barStatus": 0, "barId": 33, "postBy": {"utc": 1431751838000, "level": 0, "location": "\u65b0\u5317\u5e02\u00b7\u53f0\u7063", "avatar": "http://filestoresg1.beetalkmobile.com:8081/file/2110596133878256660", "name": "\u8449\u745e\u9a30"}, "id": 1271644}
