{"forum": {"content": "\u5be7\u975c\u611f", "images": ["http://filestoresg1.beetalkmobile.com:8081/file/0953552a3d872692e02342eb8c92e8a2", "http://filestoresg1.beetalkmobile.com:8081/file/0b480223243c00d011847fee0bb0b9b5", "http://filestoresg1.beetalkmobile.com:8081/file/a038889ad10e1b1e705437cf9bab7179", "http://filestoresg1.beetalkmobile.com:8081/file/3856317792fd39158f57e63cf6c941d0", "http://filestoresg1.beetalkmobile.com:8081/file/a5a934dfaca880130145363642eb0400"], "urls": [], "title": "\u4e09\u4ed9\u53f0"}, "threadStatus": 1, "regionId": 886, "barStatus": 0, "barId": 77, "postBy": {"utc": 1429881202000, "level": 6, "location": "\u9ad8\u96c4\u5e02\u00b7\u53f0\u7063", "avatar": "http://filestoresg1.beetalkmobile.com:8081/file/7561967156582443008", "name": "\ud83d\udcf7FILM\ud83d\udcf7"}, "id": 1106679}
