{"forum": {"content": "\u8eab\u908a\u7684\u4eba\u90fd\u8aaa\u55ae\u8eab\u6bd4\u8f03\u81ea\u7531<br />\u4ea4\u4e86\u53e6\u4e00\u534a\u96d6\u7136\u5e78\u798f \u53ef\u662f\u6703\u6709\u500b\u675f\u7e1b \u4f46\u662f \u6211\u89ba\u5f97\u55ae\u8eab\u4e5f\u662f\u6703\u5bc2\u5bde\u7684\u02ca\u02cb<br />\u4f60/\u59b3\u89ba\u5f97\u5462\uff1f<br />#\u5bb3\u6211\u90fd\u60f3\u627e\u500b\u7537\u670b\u53cb\u4e86<br />#\u53ef\u60dc\u592a\u919c\u6c92\u4eba\u8981 \u310e\u310e", "images": ["http://filestoresg1.beetalkmobile.com:8081/file/8b3d1bee2eecbddc687772ed9415cc18", "http://filestoresg1.beetalkmobile.com:8081/file/5a12fc2f4b9e696c462c6b2bbb387318", "http://filestoresg1.beetalkmobile.com:8081/file/32c85190e8aac86d3f545a757aac8b67", "http://filestoresg1.beetalkmobile.com:8081/file/3a87ca604a72a4183f9fa80227014d7d", "http://filestoresg1.beetalkmobile.com:8081/file/ae13200d97edd8cdd391727281d0a5ca"], "urls": [], "title": "\u55ae\u8eab\u4e5f\u6709\u55ae\u8eab\u7684\u5bc2\u5bde"}, "threadStatus": 1, "regionId": 886, "barStatus": 0, "barId": 383, "postBy": {"utc": 1432365967000, "level": 1, "location": "\u82d7\u6817\u7e23\u00b7\u53f0\u7063", "avatar": "http://filestoresg1.beetalkmobile.com:8081/file/-5071661202425752229", "name": "\u53e3\u7f69\u5973\u5b69\ud83d\ude09"}, "id": 1324033}
