{"forum": {"content": "\u963f\u5657\u5657", "images": ["http://filestoresg1.beetalkmobile.com:8081/file/a95cc741c70d6d60f83e7e16f1b3a6fc", "http://filestoresg1.beetalkmobile.com:8081/file/92963a89c56fca94e05d87f97b71d6c1", "http://filestoresg1.beetalkmobile.com:8081/file/5998aa087fc412da2cc5b8810fbc39dd", "http://filestoresg1.beetalkmobile.com:8081/file/f4512d05345573920907fb4eb8327d3c"], "urls": [], "title": "\u72d7\u8207\u4e3b\u4eba"}, "threadStatus": 0, "regionId": 886, "barStatus": 0, "barId": 4, "postBy": {"utc": 1432441021000, "level": 4, "location": "\u65b0\u5317\u5e02\u00b7\u53f0\u7063", "avatar": "http://filestoresg1.beetalkmobile.com:8081/file/-6103625433062849527", "name": "\u5609\u967d"}, "id": 1330208}
