{"forum": {"content": "\u597d\u807d\u560e", "images": [], "urls": [{"url": "https://youtu.be/xv7NZuZa-t8", "thumbUrl": "https://i.ytimg.com/vi/xv7NZuZa-t8/hqdefault.jpg", "description": "[\u4e2d\u5b57] 4minute (\ud3ec\ubbf8\ub2db) - \uc0b4\ub9cc\ucc0c\uace0 (\u53ea\u8b8a\u80d6\u4e86) (Only Gained Weight)", "title": "[\u4e2d\u5b57] 4minute (\ud3ec\ubbf8\ub2db) - \uc0b4\ub9cc\ucc0c\uace0 (\u53ea\u8b8a\u80d6\u4e86) (Only Gained Weight)"}], "title": "\u70ab\u96c5\u51fa\u73fe\u4e86"}, "threadStatus": 1, "regionId": 886, "barStatus": 0, "barId": 54, "postBy": {"utc": 1433936896000, "level": 6, "location": "\u53f0\u4e2d\u5e02\u00b7\u53f0\u7063", "avatar": "http://filestoresg1.beetalkmobile.com:8081/file/4146941146204129197", "name": "\u62b9\u8336"}, "id": 1452011}
