{"forum": {"content": "\u771f\u5fc3\u5c0d\u5f85\u6709\u6642\u5019\u63db\u4f86\u7684\u4e0d\u4e00\u5b9a\u662f\u540c\u7b49\u7684\u5c0d\u5f85<br />\u4f46\u6709\u4ed8\u51fa\u904e\u5c31\u7b97\u5230\u982d\u4f86\u5169\u982d\u7a7a\u6211\u4e5f\u4e0d\u5f8c\u6094<br />", "images": ["http://filestoresg1.beetalkmobile.com:8081/file/6a5f31cfedffb82af1ad5670c6656a07"], "urls": [], "title": "\u771f\u5fc3"}, "threadStatus": 0, "regionId": 886, "barStatus": 0, "barId": 383, "postBy": {"utc": 1438342642000, "level": 2, "location": "\u9ad8\u96c4\u5e02\u00b7\u53f0\u7063", "avatar": "http://filestoresg1.beetalkmobile.com:8081/file/5973172795358145787", "name": "\u8001\u516c"}, "id": 1809572}
