{"forum": {"content": "\u7f8e\u8ecd\u7d00\u5ff5\u5893\u5712", "images": ["http://filestoresg1.beetalkmobile.com:8081/file/59f36780db8f732b6fe916d35661db9c", "http://filestoresg1.beetalkmobile.com:8081/file/e33d65276703d0c428060012df72c300", "http://filestoresg1.beetalkmobile.com:8081/file/99237314aba35023b88404cccbf22de3", "http://filestoresg1.beetalkmobile.com:8081/file/99285ff39cc3db5174fefb85e8b41455", "http://filestoresg1.beetalkmobile.com:8081/file/43a7ef801cba5cfe1d1cb7cd6c4f1c3b", "http://filestoresg1.beetalkmobile.com:8081/file/3f2ade95952c206691c5ff9d0f74026d"], "urls": [], "title": "\u4e00\u500b\u4eba\u65c5\u884c  \u5c31\u9080\u65c5\u884c\u793e\u5c0e\u904a\u5145\u7576\u9ebb\u8c46"}, "threadStatus": 0, "regionId": 886, "barStatus": 0, "barId": 85, "postBy": {"utc": 1431306393000, "level": 3, "location": "\u53f0\u5357\u5e02\u00b7\u53f0\u7063", "avatar": "http://filestoresg1.beetalkmobile.com:8081/file/2204926537435232720", "name": "\u963f\u5169"}, "id": 1234147}
