{"forum": {"content": "5/22\u865f\u500b\u6027\u6703\u5f88\u50cf\u91d1\u725b\u55ce..\uff1f<br />\u5176\u5be6\u6709\u6642\u771f\u7684\u883b\u56f0\u64fe\u6211\u7684\u500b\u6027\u7684...<br />\u6709\u6642\u6703\u83ab\u540d\u7684\u958b\u5fc3\u6709\u6703\u83ab\u540d\u7684\u60b6\u60b6\u4e0d\u6a02..<br />\u5bb3...\u6709\u9ede\u56f0\u64fe<br />//\u96d9\u5b50\u7d66\u9ede\u5efa\u8b70\u5427\u02d9\u02d9", "images": ["http://filestoresg1.beetalkmobile.com:8081/file/086c0bc1b658fb878bfeea9ee2e9753c"], "urls": [], "title": "\u96d9\u5b50...\u02ca\u02c7\u02cb"}, "threadStatus": 1, "regionId": 886, "barStatus": 0, "barId": 88, "postBy": {"utc": 1429052753000, "level": 2, "location": "\u65b0\u5317\u5e02\u00b7\u53f0\u7063", "avatar": "http://filestoresg1.beetalkmobile.com:8081/file/-4467626902643131485", "name": "\u4f73\u541b\u5b89\u5167\u2764"}, "id": 1022175}
