{"forum": {"content": "\u5982\u984c <br />\u6211\u60f3\u597d\u4e45\uff1a\uff08", "images": ["http://filestoresg1.beetalkmobile.com:8081/file/7da71f192fbff9bc5a2453e4a0a5e0e8"], "urls": [], "title": "\u6c42\u89e3\uff01\uff01\uff01please\u2026"}, "threadStatus": 1, "regionId": 886, "barStatus": 0, "barId": 422, "postBy": {"utc": 1431615001000, "level": 1, "location": "\u65b0\u5317\u5e02\u00b7\u53f0\u7063", "avatar": "http://filestoresg1.beetalkmobile.com:8081/file/8653015774188946619", "name": "\u265aBellona L.\u265a"}, "id": 1261467}
