{"forum": {"content": "\u6211\u5011\u8a8d\u8b58\u4e00\u4e0b\u597d\u561b\uff1a\uff09\uff09", "images": ["http://filestoresg1.beetalkmobile.com:8081/file/faf0b7724edb50493aa861db7dd2c308"], "urls": [], "title": "\u6843\u5712\u4eba\uff01"}, "threadStatus": 0, "regionId": 886, "barStatus": 0, "barId": 205, "postBy": {"utc": 1433614213000, "level": 1, "location": "\u6843\u5712\u5e02\u00b7\u53f0\u7063", "avatar": "http://filestoresg1.beetalkmobile.com:8081/file/-2309370238029818534", "name": "Hao Min Syu"}, "id": 1426560}
