{"forum": {"content": "\u9019\u6a23\u597d\u770b\u4e86\u8a31\u591a", "images": ["http://filestoresg1.beetalkmobile.com:8081/file/bb5cf296f7e1d9036c576fe4943220da", "http://filestoresg1.beetalkmobile.com:8081/file/1b6526e8bc90e66186c5d38fba0e060e", "http://filestoresg1.beetalkmobile.com:8081/file/75f0c0e4daa6444970ddd9d71c021fae"], "urls": [], "title": "\u8d85\u30c8\u30c3\u30ad\u30e5\u30a6\u30c0\u30a4\u30aa\u30fc"}, "threadStatus": 1, "regionId": 886, "barStatus": 0, "barId": 207, "postBy": {"utc": 1435556970000, "level": 2, "location": "\u65b0\u5317\u5e02\u00b7\u53f0\u7063", "avatar": "http://filestoresg1.beetalkmobile.com:8081/file/6349783006768056385", "name": "\u5c0f\u591c"}, "id": 1586158}
