{"forum": {"content": "\u5982\u679c\u6709\u4eba\u60f3\u52a0\u5165\u6211\u7684BT\u63ea\u5718  \u79c1\u6211\u6b50 s", "images": ["http://filestoresg1.beetalkmobile.com:8081/file/d8cff0d8c90cdcb8098e921d43c50955"], "urls": [], "title": "\u63ea\u5718"}, "threadStatus": 1, "regionId": 886, "barStatus": 0, "barId": 422, "postBy": {"utc": 1436278781000, "level": 3, "location": "\u5f70\u5316\u7e23\u00b7\u53f0\u7063", "avatar": "http://filestoresg1.beetalkmobile.com:8081/file/9216365950372419154", "name": "\u2605 \u54a9\u54a9 \u2705\u5beb\u4e0d\u5b8c\u7684\u8a69"}, "id": 1644926}
