{"forum": {"content": "\u4ec0\u9ebc\u9ebb \u611b\u60c5\u52d5\u4f5c\u7247 \u7968\u9078\u6700\u9ad8<br />\u771f\u662f\u7684 \u4f60\u5011\u5728\u60f3\u4ec0\u9ebc\u52d2xdd<br /><br />\u4f86 \u9019\u662f\u4e92\u52d5\u6587 \u60f3\u5c0d\u5a1c\u5a1c\u8aaa\u4ec0\u9ebc\u901a\u901a\u7559\u8a00\u7d66\u6211\ud83d\udc95\ud83d\udc95\ud83d\udc95\ud83d\udc95\ud83d\udc95\ud83d\udc95<br />", "images": ["http://filestoresg1.beetalkmobile.com:8081/file/99603e0a90a7b9d1fce0b4f22cf96896"], "urls": [], "title": "\u6211\u90fd\u63a5\u7372\u5927\u5bb6\u7684\u5fc3\u8072\u56c9"}, "threadStatus": 1, "regionId": 886, "barStatus": 0, "barId": 32, "postBy": {"utc": 1434157446000, "level": 7, "location": "\u53f0\u5357\u5e02\u00b7\u53f0\u7063", "avatar": "http://filestoresg1.beetalkmobile.com:8081/file/-7304603298914367756", "name": "Nana"}, "id": 1469286}
