{"forum": {"content": "\u4e3b\u984c\u662f\u72fc\u795e\u5a36\u89aa( (\uff90\u00b4\u03c9`\uff90)) ", "images": ["http://filestoresg1.beetalkmobile.com:8081/file/77d26e19e397e16cfca1236d82a6bd1d"], "urls": [], "title": "\u7279\u6b8a\u651d\u5f71\u9020\u578bw"}, "threadStatus": 0, "regionId": 886, "barStatus": 0, "barId": 35, "postBy": {"utc": 1436618018000, "level": 1, "location": "\u6843\u5712\u5e02\u00b7\u53f0\u7063", "avatar": "http://filestoresg1.beetalkmobile.com:8081/file/-7057567214076664177", "name": "castie"}, "id": 1672473}
