{"forum": {"content": "\u9019\u662f\u6211\u50b3\u7d66\u5979\u73fe\u4efb\u7684\u7c21\u8a0a...<br />\u9019\u6a23\u505a\u6703\u4e0d\u6703\u5f88\u8822\uff1f", "images": ["http://filestoresg1.beetalkmobile.com:8081/file/149612dc3af812bbda7c78f3d02721e1"], "urls": [], "title": "\u5982\u679c\u56e0\u70ba\u611b\u800c\u653e\u624b\u4f60\u6703\u50b3\u8a0a\u606f\u7d66\u4ed6\u7684\u53e6\u4e00\u534a\u55ce\uff1f"}, "threadStatus": 1, "regionId": 886, "barStatus": 0, "barId": 18, "postBy": {"utc": 1433427506000, "level": 2, "location": "\u53f0\u5357\u5e02\u00b7\u53f0\u7063", "avatar": "http://filestoresg1.beetalkmobile.com:8081/file/-2535181340875555328", "name": "Yang"}, "id": 1411508}
