{"forum": {"content": "\u4f60\u5011\u5347\u7d1a\u65b0\u7248\u672c\u4e86\u55ce\uff1f", "images": ["http://filestoresg1.beetalkmobile.com:8081/file/a5bfd0d34f47767780ac5b7c6bedd004"], "urls": [], "title": "Beetalk\u6539\u7248\u4e86\uff01"}, "threadStatus": 0, "regionId": 886, "barStatus": 0, "barId": 10, "postBy": {"utc": 1435893689000, "level": 10, "location": "\u53f0\u4e2d\u5e02\u00b7\u53f0\u7063", "avatar": "http://filestoresg1.beetalkmobile.com:8081/file/8561401176031809583", "name": "\u767d\u99ac"}, "id": 1612694}
