{"forum": {"content": "\u96e3\u602a\u9b25\u725b\u7bc0\u88ab\u7981\u6b62\u4e86", "images": ["http://filestoresg1.beetalkmobile.com:8081/file/17189b4eecbbf4d750cb1ae4ab271e5f"], "urls": [], "title": "\u725b\u4e38"}, "threadStatus": 1, "regionId": 886, "barStatus": 0, "barId": 10, "postBy": {"utc": 1437612903000, "level": 39, "location": "\u53f0\u4e2d\u5e02\u00b7\u53f0\u7063", "avatar": "http://filestoresg1.beetalkmobile.com:8081/file/-4842626331237923862", "name": "\u2728\u8001\u516c \ud83d\ude08Evil\u2728"}, "id": 1750040}
