{"forum": {"content": "\u5e36\u53ef\u611b\u7684Bimo\u8207Dunk\u51fa\u4f86\u66ec\u592a\u967d\u56c9\uff0c\u7d50\u679c\u4e3b\u4eba\u5feb\u88ab\u71b1\u6b7b!!!!==", "images": ["http://filestoresg1.beetalkmobile.com:8081/file/34775632060ddb82d038d0a0667317c4", "http://filestoresg1.beetalkmobile.com:8081/file/e0afc4e09ace16f5bb379bc22714581a", "http://filestoresg1.beetalkmobile.com:8081/file/340376176cdc3937794666012a6827c9", "http://filestoresg1.beetalkmobile.com:8081/file/bedb757ce332dedcac12526a0bb3bf3d", "http://filestoresg1.beetalkmobile.com:8081/file/a3fb068a559820ff4ce86874cb900164", "http://filestoresg1.beetalkmobile.com:8081/file/16b9785c65ee53b7b5fd2456b4309801"], "urls": [], "title": "\u708e\u71b1\u7684\u65e9\u6668  \u4f86\u73a9\u500b\u98db\u76e4\u8ddf\u7403\u5427!!"}, "threadStatus": 0, "regionId": 886, "barStatus": 0, "barId": 105, "postBy": {"utc": 1429932318000, "level": 3, "location": "\u53f0\u4e2d\u5e02\u00b7\u53f0\u7063", "avatar": "http://filestoresg1.beetalkmobile.com:8081/file/695270689222634155", "name": "jungo"}, "id": 1110819}
