{"forum": {"content": "\u9ad8\u96c4\u662f\u5de5\u696d\u8d77\u5bb6\u90fd\u5e02\u4f46\u5982\u4eca\u7522\u696d\u66f4\u591a\u5143\u4e86\u2026\u597d\u5947 \u5927\u5bb6\u8077\u696d\u662f\u4ec0\u9ebc\u5462\uff1f", "images": ["http://filestoresg1.beetalkmobile.com:8081/file/e91709816a707fe57e973b5a3b45d78d"], "urls": [], "title": "\u9ad8\u96c4\u7684\u5927\u5bb6\u8077\u696d\u662f\u4ec0\u9ebc\u5462\uff1f"}, "threadStatus": 1, "regionId": 886, "barStatus": 0, "barId": 676, "postBy": {"utc": 1436113038000, "level": 3, "location": "\u6f8e\u6e56\u7e23\u00b7\u53f0\u7063", "avatar": "http://filestoresg1.beetalkmobile.com:8081/file/5705439516093041695", "name": "\u6211\u597d\u5947"}, "id": 1631412}
