{"forum": {"content": "\u5065\u5eb7\u597d\u5403", "images": ["http://filestoresg1.beetalkmobile.com:8081/file/74b22591c76085ab8cd55b78aeaa08be"], "urls": [], "title": "\u7d14\u9bae\u5976\u5de7\u514b\u529b\u51b0\u6dc7\u6dcb"}, "threadStatus": 0, "regionId": 886, "barStatus": 0, "barId": 98, "postBy": {"utc": 1438599121000, "level": 5, "location": "\u9ad8\u96c4\u5e02\u00b7\u53f0\u7063", "avatar": "http://filestoresg1.beetalkmobile.com:8081/file/3022846642636095304", "name": "\uc9c4 \uc720\ube48"}, "id": 1831147}
