{"forum": {"content": "\u6211\u7684\u523a\u9752\u60f3\u8981\u84cb\u5716\uff0c\u4e00\u76f4\u60f3\u4e0d\u5230\u8981\u7684\u5716<br /><br />\u6709\u60f3\u6b21 \u5bb6\u5ead \u81ea\u7531 \u5e0c\u671b \u734e\u52f5 \u6210\u5c31 \u9019\u4e9b\u5b57<br /><br />\u53ef\u662f\u5c31\u662f\u60f3\u4e0d\u5230\u5716\uff0c\u53ef\u5426\u5927\u5bb6\u7d66\u6211\u610f\u898b", "images": ["http://filestoresg1.beetalkmobile.com:8081/file/4e150f901d29980a06646be4977152a2", "http://filestoresg1.beetalkmobile.com:8081/file/a895f51bb8cd7f7033fe6966baa6888d"], "urls": [], "title": "\u5927\u5bb6\u597d\uff0c\u6211\u60f3\u8acb\u5404\u4f4d\u7d66\u6211\u4e00\u4e9b\u610f\u898b"}, "threadStatus": 0, "regionId": 886, "barStatus": 0, "barId": 35, "postBy": {"utc": 1438092835000, "level": 2, "location": "\u6843\u5712\u5e02\u00b7\u53f0\u7063", "avatar": "http://filestoresg1.beetalkmobile.com:8081/file/-9022682564737553143", "name": "\u73ee\u73ee"}, "id": 1789649}
