{"forum": {"content": "\u5fc3\u8840\u4f86\u6f6e~~", "images": ["http://filestoresg1.beetalkmobile.com:8081/file/477feb09b4ef7985461f6834c438ad97", "http://filestoresg1.beetalkmobile.com:8081/file/b645a4dd76020c3ee0d61cca0fa73a16", "http://filestoresg1.beetalkmobile.com:8081/file/ecf9d3fec55cf49d381b9c64c0c4e80a", "http://filestoresg1.beetalkmobile.com:8081/file/d29774c06ce0f8c80ebe40b110b3aaab", "http://filestoresg1.beetalkmobile.com:8081/file/8f5fd6c0dae7fdc3c68be6e354f997a7"], "urls": [], "title": "\u86fb\u8b8a\u3002"}, "threadStatus": 1, "regionId": 886, "barStatus": 0, "barId": 4, "postBy": {"utc": 1438071195000, "level": 0, "location": "\u9ad8\u96c4\u5e02\u00b7\u53f0\u7063", "avatar": "http://filestoresg1.beetalkmobile.com:8081/file/8280223067030441984", "name": "\u5c0f\u9ea5"}, "id": 1787342}
