{"forum": {"content": "\u99ac\u4f86\u897f\u4e9e\u7684 Monica Lee \u5c07\u771f\u5be6\u7684\u4e16\u754c\u900f\u904e\u81ea\u5df1\u756b\u7b46\u7d00\u9304\u4e0b\u4f86\uff0c\u5c0d\u7d30\u7bc0\u8d85\u7d1a\u8457\u8ff7\u7684\u5979\u8aaa\uff1a\u201cI like to challenge myself with complex portraits especially people with freckles or beard. And I\u2019m addicted to details. I like drawing in as much details as I can into my work.\u201d\u3002\u4f3c\u4e4e\u6108\u662f\u6709\u7d0b\u7406\u6108\u662f\u6709\u5370\u75d5\u7684\u81c9\u66f4\u60f9\u5979\u559c\u6b61\u3002", "images": ["http://filestoresg1.beetalkmobile.com:8081/file/5e791358f0e877808c869592cd411de1", "http://filestoresg1.beetalkmobile.com:8081/file/0e37f4faacb2b351c9b5e9b0c13fae52", "http://filestoresg1.beetalkmobile.com:8081/file/7837f7e32fae3974f14301ba3b9d48fa", "http://filestoresg1.beetalkmobile.com:8081/file/b8753984c30238f712baf1ab6987bd15", "http://filestoresg1.beetalkmobile.com:8081/file/bbaf2f3da7f2beb638508f1a5390fbb6"], "urls": [], "title": "\u8d85\u7d1a\u771f\u5be6\u7684\u795e\u7d1a\u7d20\u63cf"}, "threadStatus": 0, "regionId": 886, "barStatus": 0, "barId": 35, "postBy": {"utc": 1430200377000, "level": 12, "location": "", "avatar": "http://filestoresg1.beetalkmobile.com:8081/file/-183356758042930808", "name": "dkmom"}, "id": 1136941}
