{"forum": {"content": "\u4f60\u4e5f\u592a\u80a5\u4e86\u5427", "images": ["http://filestoresg1.beetalkmobile.com:8081/file/471568006eeddba731a737addcc1a89b", "http://filestoresg1.beetalkmobile.com:8081/file/26f08e2abfbd0d3e86bde189a8faa095", "http://filestoresg1.beetalkmobile.com:8081/file/e8969c9d353cb5b0b1a6235b84682268"], "urls": [], "title": "\u53c8\u80d6\u4e86"}, "threadStatus": 0, "regionId": 886, "barStatus": 0, "barId": 105, "postBy": {"utc": 1429462207000, "level": 1, "location": "\u5f70\u5316\u7e23\u00b7\u53f0\u7063", "avatar": "http://filestoresg1.beetalkmobile.com:8081/file/-3673733328929907712", "name": "\u5c0f\u6f58"}, "id": 1063897}
