{"forum": {"content": "\u4e0d\u7136\u8981\u5e79\u561b", "images": ["http://filestoresg1.beetalkmobile.com:8081/file/eafa9fd8af5e8db07847cd21f2617a60"], "urls": [], "title": "\u98b1\u98a8\u5929\u5c31\u662f\u8981\u6563\u6b65\u554a"}, "threadStatus": 0, "regionId": 886, "barStatus": 0, "barId": 105, "postBy": {"utc": 1440333504000, "level": 7, "location": "\u5b9c\u862d\u7e23\u00b7\u53f0\u7063", "avatar": "http://filestoresg1.beetalkmobile.com:8081/file/-6680638134649393149", "name": "Eric Chiang"}, "id": 1971981}
