{"forum": {"content": "\u56e0\u70ba\u98b1\u98a8\u9031\uff0c\u5c0e\u81f4\u51fa\u904a\u5ef6\u671f\uff5e\ud83d\ude22<br />\u8d81\u8457\u5e25\u5b85\u5b85\u9019\u5169\u5929\u653e\u5047\uff0c\u5c31\u4f86\u597d\u597d\u7684\u9935\u98df\u4ed6\u56c9\uff01\ud83d\udc8b<br />\u5148\u4f86\u71c9\u4e00\u934b\u4ed6\u611b\u559d\u7684\u863f\u8514\u6e6f\uff5e\ud83d\ude1a<br /><br />\u6211\u597d\u8ce2\u6167\u963f\uff5e\ud83d\ude18<br />\u4f60\u5011\u8aaa\u662f\u4e0d\u662f\uff01\u662f\u4e0d\u662f\uff01\u662f\u4e0d\u662f\uff01\ud83d\ude01", "images": ["http://filestoresg1.beetalkmobile.com:8081/file/0bdd76c1fb16dc31c39937b5bfa866dc"], "urls": [], "title": "\u863f\u8514\u554a\u863f\u8514"}, "threadStatus": 0, "regionId": 886, "barStatus": 0, "barId": 422, "postBy": {"utc": 1436340837000, "level": 17, "location": "\u65b0\u7af9\u5e02\u00b7\u53f0\u7063", "avatar": "http://filestoresg1.beetalkmobile.com:8081/file/7011847343514785036", "name": "\u82b1\u7530\u9ebb\u7cec\ud83c\udf61"}, "id": 1649771}
