{"forum": {"content": "\u4f60\u5011\u90fd\u559c\u6b61\u4ec0\u9ebc\u6a23\u5b50\u7684\u5973\u751f\uff1f", "images": ["http://filestoresg1.beetalkmobile.com:8081/file/8e2129eaae3b0f1101a71c7a7d6abe61"], "urls": [], "title": "\u665a\u5b89\ud83d\ude01"}, "threadStatus": 0, "regionId": 886, "barStatus": 0, "barId": 4, "postBy": {"utc": 1434635512000, "level": 2, "location": "\u5b9c\u862d\u7e23\u00b7\u53f0\u7063", "avatar": "http://filestoresg1.beetalkmobile.com:8081/file/-4212079508132282501", "name": "\u311a\u65b9\u65b9"}, "id": 1509040}
