{"forum": {"content": "\u5982\u984c!<br />\u8aaa\u8aaa\u4f60(\u59b3)\u5011\u7684\u60f3\u6cd5\u6216\u662f\u505a\u6cd5?", "images": [], "urls": [{"url": "https://m.youtube.com/watch?v=p_jsrarbpQ4&feature=youtu.be", "thumbUrl": "https://i.ytimg.com/vi/p_jsrarbpQ4/default.jpg", "description": "\u300a\u7231\u8981\u600e\u4e48\u8bf4\u300b\u3000\n\u5531\uff1a\u4f0d\u601d\u51ef\u3000\n\u8bcd\uff1a\u6797\u79cb\u79bb\u3000\n\u66f2\uff1a\u674e\u58eb\u5148\u3000\n\n\u7231\u4e0a\u4e86\u4ec0\u4e48\u6837\u7684\u6211\u3000\u4f60\u5e94\u8be5\u77e5\u9053\u3000\n\u5f53\u4f60\u6d41\u6cea\u7684\u65f6\u5019\u3000\u6068\u4e0d\u6068\u6211\u3000\n\n\u7231\u4e0a\u4e86\u4ec0\u4e48\u6837\u7684\u6211\u3000\u4f60\u5e94\u8be5\u60f3\u8fc7\u3000\n\u5f53\u6211\u79bb\u53bb\u7684\u65f6\u5019\u3000\u4e0d\u8981\u96be\u8fc7\u3000\n\n\u4e3a\u4f55\u4e00\u5b9a\u8981\u8fd9\u6837", "title": "\u4f0d\u601d\u51ef - \u300a\u7231\u8981\u600e\u4e48\u8bf4\u300b (\u539f\u88c5\u7ecf\u5178\u7248\u672c)"}], "title": "\u611b\u8981\u600e\u9ebc\u8aaa?"}, "threadStatus": 0, "regionId": 886, "barStatus": 0, "barId": 13, "postBy": {"utc": 1438944754000, "level": 1, "location": "", "avatar": "http://filestoresg1.beetalkmobile.com:8081/file/3339310278785097077", "name": "\u5438\u8840\u5973\u50d5 \ud83d\udc57"}, "id": 1859374}
