{"forum": {"content": "\u6b61\u8fce\u8a8d\u8b58\u96d9\u5b50\u5ea7", "images": ["http://filestoresg1.beetalkmobile.com:8081/file/6190e6d825c31840a1ce17203225cc65"], "urls": [], "title": "\u4eba\u771f\u96e3\u641e"}, "threadStatus": 1, "regionId": 886, "barStatus": 0, "barId": 4, "postBy": {"utc": 1437298386000, "level": 1, "location": "\u53f0\u5317\u5e02\u00b7\u53f0\u7063", "avatar": "http://filestoresg1.beetalkmobile.com:8081/file/-7682992528014760960", "name": "\u4f60\u554f\u6211\u7b54"}, "id": 1725296}
