{"forum": {"content": "high 175 \ud83d\ude1e\ud83d\ude1e\ud83d\ude1e<br />Yulin -\u5927\u4e09- <br /><br />\u7b97\u662f\u507d\u5a18\u2026\u5427\uff09<br />\u5f9e\u5fc3\u958b\u59cb\u2026\uff1f\uff09", "images": ["http://filestoresg1.beetalkmobile.com:8081/file/2e29c57c5bd4c1d59857e15555fcebd0"], "urls": [], "title": "\u6211\u662f\u7537\u751f\ud83d\udc08\u5973\u8072 \ud83c\udfa4"}, "threadStatus": 1, "regionId": 886, "barStatus": 0, "barId": 20, "postBy": {"utc": 1431331793000, "level": 11, "location": "\u96f2\u6797\u7e23\u00b7\u53f0\u7063", "avatar": "http://filestoresg1.beetalkmobile.com:8081/file/-6301264847074872326", "name": "quiet"}, "id": 1236496}
