{"forum": {"content": "\u6211\u5e25\u7684\u5730\u65b9\u4e0d\u662f\u81c9\uff0c\u800c\u662f\u5fc3\u8207\u8eab\u6750\u3002", "images": ["http://filestoresg1.beetalkmobile.com:8081/file/77d598037aeebc9d1150e6e1e3145512", "http://filestoresg1.beetalkmobile.com:8081/file/e778209e7f815e55694b9ab01f9c4aea", "http://filestoresg1.beetalkmobile.com:8081/file/01a9de667a2df758d87eef00ff6de9aa", "http://filestoresg1.beetalkmobile.com:8081/file/890446890a16b54657aa174e40fb4732", "http://filestoresg1.beetalkmobile.com:8081/file/600acb08c49404a8a2e21826f7495a7b", "http://filestoresg1.beetalkmobile.com:8081/file/56d534288dc8492cd5d227ed44c8f412"], "urls": [], "title": "\u5e25\u90a3\u88e1"}, "threadStatus": 0, "regionId": 886, "barStatus": 0, "barId": 33, "postBy": {"utc": 1429016632000, "level": 2, "location": "\u65b0\u5317\u5e02\u00b7\u53f0\u7063", "avatar": "http://filestoresg1.beetalkmobile.com:8081/file/7677580735481099924", "name": "Kevin885511"}, "id": 1019157}
