{"forum": {"content": "\u6afb\u82b1\u5712", "images": ["http://filestoresg1.beetalkmobile.com:8081/file/d65cd9f85786cccdb3d83d07abdf7eaa", "http://filestoresg1.beetalkmobile.com:8081/file/74db9179f2dcc53499080417b2a41e48", "http://filestoresg1.beetalkmobile.com:8081/file/dd678ee5b5522445d51892ddcc744fad", "http://filestoresg1.beetalkmobile.com:8081/file/7033607364306ee60779498255a9cc9d", "http://filestoresg1.beetalkmobile.com:8081/file/d181a542a918b656e9986958e1b49003", "http://filestoresg1.beetalkmobile.com:8081/file/c57632047f2d8e81a11fdd8b0595db4e"], "urls": [], "title": "\u5317\u6d77\u9053~\u5de7\u9047\u6afb\u82b1\u5712"}, "threadStatus": 0, "regionId": 886, "barStatus": 0, "barId": 87, "postBy": {"utc": 1433689281000, "level": 3, "location": "\u65b0\u7af9\u7e23\u00b7\u53f0\u7063", "avatar": "http://filestoresg1.beetalkmobile.com:8081/file/-3287109853043920569", "name": "000000000009"}, "id": 1432447}
