{"forum": {"content": "\u4e00\u591c\u60c5\u5c31\u662f\u4e00\u591c\u4e4b\u5f8c\u4e0d\u7559\u60c5<br />\u70ba\u4ec0\u9ebc\u7537\u751f\u90a3\u9ebc\u611b\u4e00\u591c\u60c5\uff1f<br />\u6709\u4e86\u5973\u53cb\u6216\u8001\u5a46<br />\u61c9\u8a72\u5b89\u5206\u624d\u5c0d\u5427\uff01", "images": ["http://filestoresg1.beetalkmobile.com:8081/file/1de2cd554d6c9d55626c25a4cb983f88"], "urls": [], "title": "\u4e00\u591c\u60c5"}, "threadStatus": 1, "regionId": 886, "barStatus": 0, "barId": 13, "postBy": {"utc": 1432636870000, "level": 10, "location": "\u5609\u7fa9\u5e02\u00b7\u53f0\u7063", "avatar": "http://filestoresg1.beetalkmobile.com:8081/file/-7662342600689563707", "name": "\u58eb\u53ef\u6bba \u4e0d\u53ef\u8fb1"}, "id": 1346842}
