{"forum": {"content": "\u59b3\u8aaa\u8981\u6211\u7b49\u59b3<br />\u7b49\u5230\u7684\u662f\u59b3\u8ddf\u5225\u4eba\u7761\u4e86\u4e00\u5e74...<br />\u771f\u7684\u4ee5\u70ba\u662f\u60f3\u8b93\u6211\u5011\u7684\u601d\u60f3\u884c\u70ba\u5404\u6709\u6210\u9577", "images": ["http://filestoresg1.beetalkmobile.com:8081/file/b88b95fbacd4ec029fcdf6a2120ee2e7"], "urls": [], "title": "\u55ae\u7d14\u7684\u611f\u60c5\u4ee5\u70ba\u5f88\u7c21\u55ae"}, "threadStatus": 0, "regionId": 886, "barStatus": 0, "barId": 13, "postBy": {"utc": 1440218589000, "level": 1, "location": "\u65b0\u5317\u5e02\u00b7\u53f0\u7063", "avatar": "http://filestoresg1.beetalkmobile.com:8081/file/-5231228929070704086", "name": "\u89aa\u611b\u7684\u3002"}, "id": 1962295}
