{"forum": {"content": "\u611b\u6253ball<br /><br />\u5927\u5bb6\u5b78\u6e2c\u8981\u52a0\u6cb9\u54c8\u54c8\u54c8", "images": ["http://filestoresg1.beetalkmobile.com:8081/file/b4e2d6fee702e0c704c1d7ac97601b22", "http://filestoresg1.beetalkmobile.com:8081/file/b0025b24e82a16aaa94473f7f1c2b0aa"], "urls": [], "title": "\u5b78\u6e2c\u6230\u58eb"}, "threadStatus": 1, "regionId": 886, "barStatus": 0, "barId": 438, "postBy": {"utc": 1439474313000, "level": 3, "location": "\u65b0\u5317\u5e02\u00b7\u53f0\u7063", "avatar": "http://filestoresg1.beetalkmobile.com:8081/file/110914339628001121", "name": "mac"}, "id": 1902731}
