{"forum": {"content": "\u53ef\u4ee5\u7565\u904e\u7b2c\u4e00\u5f35\u7167\u7247\u54c8\u54c8\u54c8<br /><br />\u9019\u662f\u525b\u5275\u7684\ud83d\ude06\ud83d\ude06\ud83d\ude06<br />\u6211\u5011\u53ea\u6536\u5973\u5b69\u54e6\ud83d\ude01\ud83d\ude01\ud83d\ude01<br />\u60f3\u9032\u4f86\u53ef\u4ee5\u7559\u8a00\u6216\u52a0\u6211\u597d\u53cb\u270c<br />\u6703\u6311\u4eba\u54e6\ud83d\ude05  \u6211\u5f88\u6311\u7684\ud83d\ude33\ud83d\ude33<br />\u7f3a\u7ba1\u7406\u54e1\ud83d\ude1a\ud83d\ude1a\ud83d\ude1a  \u5feb\u62c9\ud83d\ude09\ud83d\ude09", "images": ["http://filestoresg1.beetalkmobile.com:8081/file/deac3edc518854c172adb950026d8f24", "http://filestoresg1.beetalkmobile.com:8081/file/6f43dab0a2883ae82bbf645ca7aa67bf"], "urls": [], "title": "\u4f86\u6211\u7684\u63ea\u5718\u5427\ud83d\udc49\ud83d\udc48"}, "threadStatus": 1, "regionId": 886, "barStatus": 0, "barId": 208, "postBy": {"utc": 1438671420000, "level": 3, "location": "\u5f70\u5316\u7e23\u00b7\u53f0\u7063", "avatar": "http://filestoresg1.beetalkmobile.com:8081/file/-4541865929257807525", "name": "\u5440\ud83d\udc8b"}, "id": 1836873}
