{"forum": {"content": "\ud83c\udde8\ud83c\uddfa\ud83c\uddf9\ud83c\uddea \u2661 \ud83c\udd52\ud83c\udd64\ud83c\udd63\ud83c\udd54 \u2661 \u00a2\u03c5\u0442\u0454", "images": [], "urls": [{"url": "http://www.ainakstyle.com/#!3C-\uf8ff-iOS-\u8d85\u840c\u82f1\u6587\u5b57\u9ad4-APP\uff5cFancy-Key/cmbz/554b613c0cf2adc1ad1764f7", "thumbUrl": "http://static.parastorage.com/media/51ef04_2d480ee950c94ee09952851365864504.jpg_256", "description": "\u3010 Hello\uff01\uc5ec\ub7ec\ubd84 \uc548\ub155\ud558\uc138\uc694 \u2661 Welcome to \u300e\u53f0\u97d3\u6df7\u8840\u30fbAiNa OFFiCE\u300f \u3011 \u00a0 \u00a0 \u4eca\u5929\u6709\u7db2\u53cb\u79c1\u8a0a\u554f\u6211\u8aaa\uff1a \u00a0 \u6211\u5c31\u4e0b\u73ed\u5f8c\u706b\u901f\u751f\u51fa\u9019\u53ef\u611b\u7684\u82f1\u6587\uff21\uff30\uff30\u7684\u4ecb\u7d39\u6587\uff5e \u00a0 \u9996\u5148", "title": "3C \uf8ff iOS \u8d85\u840c\u82f1\u6587\u5b57\u9ad4 APP\uff5cFancy Key | AiNa OFFiCE"}], "title": "3C \uf8ff iOS \u8d85\u840c\u82f1\u6587\u5b57\u9ad4 APP\uff5cFancy Key"}, "threadStatus": 0, "regionId": 886, "barStatus": 0, "barId": 74, "postBy": {"utc": 1431072336000, "level": 3, "location": "\u53f0\u5317\u5e02\u00b7\u53f0\u7063", "avatar": "http://filestoresg1.beetalkmobile.com:8081/file/3762999384165016072", "name": "\u97d3\u5f0f\u8c93\u62cc\u98ef"}, "id": 1214460}
