{"forum": {"content": "\u534a\u591c\u7761\u4e0d\u8457\u53ef\u4ee5\u8ddf\u6211\u4e00\u8d77\u800d\u5ee2", "images": ["http://filestoresg1.beetalkmobile.com:8081/file/fee8e41674f26f238b4b31704b83fca9"], "urls": [], "title": "\u7562\u696d\u751f"}, "threadStatus": 1, "regionId": 886, "barStatus": 0, "barId": 438, "postBy": {"utc": 1436894849000, "level": 1, "location": "\u6843\u5712\u5e02\u00b7\u53f0\u7063", "avatar": "http://filestoresg1.beetalkmobile.com:8081/file/-4584168539424827693", "name": "\u50bbb"}, "id": 1695724}
