{"forum": {"content": "\u4eca\u5929\u9280\u8272\u60c5\u4eba\u7bc0<br />\u795d\u5927\u5bb6\u60c5\u4eba\u7bc0\u5feb\u6a02\ud83d\ude18", "images": ["http://filestoresg1.beetalkmobile.com:8081/file/60fb1cd4a77461c8fa991df5e43653a4"], "urls": [], "title": "\u4f60\u5011\u597d\u5440"}, "threadStatus": 1, "regionId": 886, "barStatus": 0, "barId": 4, "postBy": {"utc": 1436888316000, "level": 6, "location": "\u6843\u5712\u5e02\u00b7\u53f0\u7063", "avatar": "http://filestoresg1.beetalkmobile.com:8081/file/-5070978407877130921", "name": "\u964c\u751f\u4eba\ud83d\ude0e\ud83d\ude0e"}, "id": 1695045}
