{"forum": {"content": "\u597d\u4e45\u6c92\u56de\u4f86Bee\u4e86<br />\u982d\u9aee\u77ed\u4e00\u7bc0", "images": ["http://filestoresg1.beetalkmobile.com:8081/file/7b8452bcbdbd6a45f7299404131e0c81", "http://filestoresg1.beetalkmobile.com:8081/file/0c7bcfca1bb98a1f2f5a8b2c974dcdeb", "http://filestoresg1.beetalkmobile.com:8081/file/d5e5877ea4a79ee94d39e0c389e549fe", "http://filestoresg1.beetalkmobile.com:8081/file/066401f0454eb7f32a9d02f8e7057e47"], "urls": [], "title": "\u570b\u4e8c((\u8981\u904e\u4e09\u560d~"}, "threadStatus": 0, "regionId": 886, "barStatus": 0, "barId": 512, "postBy": {"utc": 1435160980000, "level": 4, "location": "\u53f0\u5357\u5e02\u00b7\u53f0\u7063", "avatar": "http://filestoresg1.beetalkmobile.com:8081/file/-9007851263254523326", "name": "\u8a9e\u99a8"}, "id": 1554004}
